{
"type": "FeatureCollection",
"name": "geom_ctr_reg",
"crs": { "type": "name", "properties": { "name": "urn:ogc:def:crs:OGC:1.3:CRS84" } },
"features": [
{ "type": "Feature", "properties": { "insee_reg": "01", "lib_reg": "Guadeloupe" }, "geometry": { "type": "Point", "coordinates": [ -61.539863970093414, 16.197655628844164 ] } },
{ "type": "Feature", "properties": { "insee_reg": "02", "lib_reg": "Martinique" }, "geometry": { "type": "Point", "coordinates": [ -61.019611234323243, 14.654897402310562 ] } },
{ "type": "Feature", "properties": { "insee_reg": "03", "lib_reg": "Guyane" }, "geometry": { "type": "Point", "coordinates": [ -53.237712294069844, 3.922060670769425 ] } },
{ "type": "Feature", "properties": { "insee_reg": "04", "lib_reg": "La Réunion" }, "geometry": { "type": "Point", "coordinates": [ 55.532518396183427, -21.133216088566201 ] } },
{ "type": "Feature", "properties": { "insee_reg": "06", "lib_reg": "Mayotte" }, "geometry": { "type": "Point", "coordinates": [ 45.147364453253317, -12.820655090736881 ] } },
{ "type": "Feature", "properties": { "insee_reg": "11", "lib_reg": "Île-de-France" }, "geometry": { "type": "Point", "coordinates": [ 2.503400734142917, 48.709307684057649 ] } },
{ "type": "Feature", "properties": { "insee_reg": "24", "lib_reg": "Centre-Val de Loire" }, "geometry": { "type": "Point", "coordinates": [ 1.684416773013259, 47.484795259803242 ] } },
{ "type": "Feature", "properties": { "insee_reg": "27", "lib_reg": "Bourgogne-Franche-Comté" }, "geometry": { "type": "Point", "coordinates": [ 4.806761907639678, 47.234276355167935 ] } },
{ "type": "Feature", "properties": { "insee_reg": "28", "lib_reg": "Normandie" }, "geometry": { "type": "Point", "coordinates": [ 0.11107271148063, 49.120080854633095 ] } },
{ "type": "Feature", "properties": { "insee_reg": "32", "lib_reg": "Hauts-de-France" }, "geometry": { "type": "Point", "coordinates": [ 2.771349977316697, 49.969508325410516 ] } },
{ "type": "Feature", "properties": { "insee_reg": "44", "lib_reg": "Grand Est" }, "geometry": { "type": "Point", "coordinates": [ 5.613005337720599, 48.688915694110655 ] } },
{ "type": "Feature", "properties": { "insee_reg": "52", "lib_reg": "Pays de la Loire" }, "geometry": { "type": "Point", "coordinates": [ -0.816703258289273, 47.478105907482572 ] } },
{ "type": "Feature", "properties": { "insee_reg": "53", "lib_reg": "Bretagne" }, "geometry": { "type": "Point", "coordinates": [ -2.840476564844098, 48.177239982992667 ] } },
{ "type": "Feature", "properties": { "insee_reg": "75", "lib_reg": "Nouvelle-Aquitaine" }, "geometry": { "type": "Point", "coordinates": [ 0.207676922265311, 45.206873649713636 ] } },
{ "type": "Feature", "properties": { "insee_reg": "76", "lib_reg": "Occitanie" }, "geometry": { "type": "Point", "coordinates": [ 2.14394296092809, 43.702479406259961 ] } },
{ "type": "Feature", "properties": { "insee_reg": "84", "lib_reg": "Auvergne-Rhône-Alpes" }, "geometry": { "type": "Point", "coordinates": [ 4.535995051103167, 45.514650947891241 ] } },
{ "type": "Feature", "properties": { "insee_reg": "93", "lib_reg": "Provence-Alpes-Côte d'Azur" }, "geometry": { "type": "Point", "coordinates": [ 6.060867499249226, 43.959073224908202 ] } },
{ "type": "Feature", "properties": { "insee_reg": "94", "lib_reg": "Corse" }, "geometry": { "type": "Point", "coordinates": [ 9.106570672273062, 42.151783779114965 ] } }
]
}
